xkcd_bot/XkcdBot.py
xkcd_bot/XkcdCommandParser.py
xkcd_bot/__init__.py
xkcd_bot/db/Comic.py
xkcd_bot/db/Subscription.py
xkcd_bot/db/__init__.py
xkcd_bot-0.2.1.data/scripts/backup.sh
xkcd_bot-0.2.1.data/scripts/restore.sh
xkcd_bot-0.2.1.data/scripts/xkcd-bot
xkcd_bot-0.2.1.dist-info/LICENSE
xkcd_bot-0.2.1.dist-info/METADATA
xkcd_bot-0.2.1.dist-info/WHEEL
xkcd_bot-0.2.1.dist-info/top_level.txt
xkcd_bot-0.2.1.dist-info/RECORD
