Metadata-Version: 2.1
Name: xkcd-bot
Version: 0.2.1
Summary: A kudubot for XKCD comics
Home-page: https://gitlab.namibsun.net/namibsun/python/xkcd-bot
Author: Hermann Krumrey
Author-email: hermann@krumreyh.com
License: GNU GPL3
Platform: UNKNOWN
Classifier: License :: OSI Approved :: GNU General Public License v3 (GPLv3)
Requires-Dist: typing
Requires-Dist: requests
Requires-Dist: bokkichat
Requires-Dist: kudubot
Requires-Dist: sqlalchemy
Requires-Dist: bs4
Requires-Dist: sentry-sdk
